[
  {
    "model": "extra_trees",
    "accuracy": 0.6312380038387716,
    "f1_macro": 0.6113196945876368,
    "family": "ML"
  },
  {
    "model": "rf",
    "accuracy": 0.6317178502879078,
    "f1_macro": 0.6111427222089945,
    "family": "ML"
  },
  {
    "model": "linear_svm",
    "accuracy": 0.5959692898272553,
    "f1_macro": 0.5642009866674557,
    "family": "ML"
  },
  {
    "model": "logreg",
    "accuracy": 0.5863723608445297,
    "f1_macro": 0.5558321731236254,
    "family": "ML"
  },
  {
    "model": "tiny_cnn",
    "accuracy": 0.48133333333333334,
    "f1_macro": 0.43029350975526387,
    "family": "DL"
  }
]